__init__.py
binary_rain_helper_toolkit/__init__.py
binary_rain_helper_toolkit/cloud/__init__.py
binary_rain_helper_toolkit/cloud/azure.py
binary_rain_helper_toolkit/cloud/graph.py
binary_rain_helper_toolkit/data_processing/dataframe.py
binary_rain_helper_toolkit/environment/__init__.py
binary_rain_helper_toolkit/environment/env.py
binary_rain_helper_buddy-0.0.1.dist-info/LICENSE
binary_rain_helper_buddy-0.0.1.dist-info/METADATA
binary_rain_helper_buddy-0.0.1.dist-info/WHEEL
binary_rain_helper_buddy-0.0.1.dist-info/top_level.txt
binary_rain_helper_buddy-0.0.1.dist-info/RECORD
