Metadata-Version: 2.1
Name: binary_rain_helper_buddy
Version: 0.0.1
Summary: Aims to simplify and help with commonly used functions in the cloud and data processing areas.
Author: Binary Rain, Marcel-TO
License: MIT License
Project-URL: Homepage, https://github.com/binaryrain-net
Keywords: common,help,functions,cloud,data processing,azure,aws
Classifier: License :: OSI Approved :: MIT License
Classifier: Programming Language :: Python
Classifier: Programming Language :: Python :: 3
Requires-Python: >=3.11
License-File: LICENSE
